cossif/__init__.py
cossif/cossif.py
cossif-0.0.3.dist-info/LICENSE
cossif-0.0.3.dist-info/METADATA
cossif-0.0.3.dist-info/WHEEL
cossif-0.0.3.dist-info/top_level.txt
cossif-0.0.3.dist-info/RECORD
